server/__init__.py
server/metaclasses.py
server/server3.py
server/common/__init__.py
server/common/decorator.py
server/common/descriptrs.py
server/common/errors.py
server/common/utils.py
server/common/veriables.py
server/logs/__init__.py
server/logs/config_client_log.py
server/logs/config_server_log.py
server/server/__init__.py
server/server/add_user.py
server/server/config_window.py
server/server/core.py
server/server/main_window.py
server/server/remove_user.py
server/server/server_db_decl.py
server/server/stat_window.py
server_mess-0.1.1.dist-info/METADATA
server_mess-0.1.1.dist-info/WHEEL
server_mess-0.1.1.dist-info/top_level.txt
server_mess-0.1.1.dist-info/RECORD
